package_one/__init__.py
package_one/hello_world.py
package_one/test/__init__.py
package_one/test/test_hello_world.py
package_one-0.4.dist-info/LICENSE
package_one-0.4.dist-info/METADATA
package_one-0.4.dist-info/WHEEL
package_one-0.4.dist-info/entry_points.txt
package_one-0.4.dist-info/top_level.txt
package_one-0.4.dist-info/RECORD
